glue_astronomy/__init__.py
glue_astronomy/conftest.py
glue_astronomy/spectral_coordinates.py
glue_astronomy/version.py
glue_astronomy/data/__init__.py
glue_astronomy/data/hips.py
glue_astronomy/data/tests/__init__.py
glue_astronomy/data/tests/test_hips.py
glue_astronomy/io/__init__.py
glue_astronomy/io/spectral_cube/__init__.py
glue_astronomy/io/spectral_cube/spectral_cube.py
glue_astronomy/io/spectral_cube/tests/__init__.py
glue_astronomy/io/spectral_cube/tests/test_spectral_cube.py
glue_astronomy/io/spectral_cube/tests/data/cube_3d.fits
glue_astronomy/io/spectral_cube/tests/data/cube_4d.fits
glue_astronomy/io/spectral_cube/tests/data/cube_4d_fullstokes.fits
glue_astronomy/io/spectral_cube/tests/data/cube_3d.image/table.dat
glue_astronomy/io/spectral_cube/tests/data/cube_3d.image/table.f0
glue_astronomy/io/spectral_cube/tests/data/cube_3d.image/table.f0_TSM0
glue_astronomy/io/spectral_cube/tests/data/cube_3d.image/table.info
glue_astronomy/io/spectral_cube/tests/data/cube_3d.image/table.lock
glue_astronomy/io/spectral_cube/tests/data/cube_3d.image/logtable/table.dat
glue_astronomy/io/spectral_cube/tests/data/cube_3d.image/logtable/table.f0
glue_astronomy/io/spectral_cube/tests/data/cube_3d.image/logtable/table.info
glue_astronomy/io/spectral_cube/tests/data/cube_3d.image/logtable/table.lock
glue_astronomy/io/spectral_cube/tests/data/cube_3d.image/mask0/table.dat
glue_astronomy/io/spectral_cube/tests/data/cube_3d.image/mask0/table.f0
glue_astronomy/io/spectral_cube/tests/data/cube_3d.image/mask0/table.f0_TSM0
glue_astronomy/io/spectral_cube/tests/data/cube_3d.image/mask0/table.info
glue_astronomy/io/spectral_cube/tests/data/cube_3d.image/mask0/table.lock
glue_astronomy/tests/__init__.py
glue_astronomy/tests/test_spectral_coordinates.py
glue_astronomy/translators/__init__.py
glue_astronomy/translators/astropy_table.py
glue_astronomy/translators/nddata.py
glue_astronomy/translators/regions.py
glue_astronomy/translators/spectral_cube.py
glue_astronomy-0.14.0.dist-info/licenses/LICENSE
glue_astronomy-0.14.0.dist-info/METADATA
glue_astronomy-0.14.0.dist-info/WHEEL
glue_astronomy-0.14.0.dist-info/entry_points.txt
glue_astronomy-0.14.0.dist-info/top_level.txt
glue_astronomy-0.14.0.dist-info/RECORD
