Metadata-Version: 2.4
Name: glue-astronomy
Version: 0.14.0
Summary: Astronomy-specific plugins for glue
Home-page: https://github.com/glue-viz/glue-astronomy
Author: Thomas Robitaille
Author-email: glue.viz@gmail.com
License: BSD 3-Clause License
Provides: glue_astronomy
Requires-Python: >=3.10
License-File: LICENSE
Requires-Dist: astropy>=4.0
Requires-Dist: glue-core>=1.6.1
Requires-Dist: regions>=0.4
Requires-Dist: specutils>=1.20
Requires-Dist: specreduce>=1.0.0
Requires-Dist: spectral-cube>=0.6.0
Provides-Extra: docs
Requires-Dist: sphinx; extra == "docs"
Requires-Dist: sphinx-automodapi; extra == "docs"
Requires-Dist: sphinxcontrib-spelling; extra == "docs"
Requires-Dist: numpydoc; extra == "docs"
Requires-Dist: sphinx-rtd-theme; extra == "docs"
Provides-Extra: hips
Requires-Dist: reproject>=0.16.0; python_version >= "3.11" and extra == "hips"
Provides-Extra: test
Requires-Dist: pytest; extra == "test"
Requires-Dist: pytest-astropy; extra == "test"
Requires-Dist: pytest-cov; extra == "test"
Requires-Dist: mock; extra == "test"
Provides-Extra: qt
Requires-Dist: PyQt5; extra == "qt"
Provides-Extra: visualtest
Requires-Dist: pytest-mpl; extra == "visualtest"
Dynamic: license-file
Dynamic: provides
